roboflow/__init__.py
roboflow/config.py
roboflow/deployment.py
roboflow/roboflowpy.py
roboflow/adapters/__init__.py
roboflow/adapters/deploymentapi.py
roboflow/adapters/rfapi.py
roboflow/core/__init__.py
roboflow/core/dataset.py
roboflow/core/model.py
roboflow/core/project.py
roboflow/core/version.py
roboflow/core/workspace.py
roboflow/models/__init__.py
roboflow/models/classification.py
roboflow/models/clip.py
roboflow/models/gaze.py
roboflow/models/inference.py
roboflow/models/instance_segmentation.py
roboflow/models/keypoint_detection.py
roboflow/models/object_detection.py
roboflow/models/semantic_segmentation.py
roboflow/models/video.py
roboflow/util/__init__.py
roboflow/util/active_learning_utils.py
roboflow/util/annotations.py
roboflow/util/clip_compare_utils.py
roboflow/util/folderparser.py
roboflow/util/general.py
roboflow/util/image_utils.py
roboflow/util/model_processor.py
roboflow/util/prediction.py
roboflow/util/two_stage_utils.py
roboflow/util/versions.py
tests/models/__init__.py
tests/models/test_instance_segmentation.py
tests/models/test_keypoint_detection.py
tests/models/test_object_detection.py
tests/models/test_semantic_segmentation.py
tests/util/__init__.py
tests/util/test_folderparser.py
tests/util/test_image_utils.py
tests/util/test_versions.py
tests/util/dummy_module/__init__.py
roboflow-1.2.13.dist-info/LICENSE
roboflow-1.2.13.dist-info/METADATA
roboflow-1.2.13.dist-info/WHEEL
roboflow-1.2.13.dist-info/entry_points.txt
roboflow-1.2.13.dist-info/top_level.txt
roboflow-1.2.13.dist-info/RECORD
