Metadata-Version: 2.1
Name: roboflow
Version: 1.2.13
Summary: Official Python package for working with the Roboflow API
Home-page: https://github.com/roboflow-ai/roboflow-python
Author: Roboflow
Author-email: support@roboflow.com
License: UNKNOWN
Platform: UNKNOWN
Classifier: Programming Language :: Python :: 3
Classifier: License :: OSI Approved :: Apache Software License
Classifier: Operating System :: OS Independent
Requires-Python: >=3.8
Requires-Dist: certifi
Requires-Dist: idna==3.7
Requires-Dist: cycler
Requires-Dist: kiwisolver>=1.3.1
Requires-Dist: matplotlib
Requires-Dist: numpy>=1.18.5
Requires-Dist: opencv-python-headless==4.10.0.84
Requires-Dist: Pillow>=7.1.2
Requires-Dist: pillow-avif-plugin<2
Requires-Dist: python-dateutil
Requires-Dist: python-dotenv
Requires-Dist: requests
Requires-Dist: six
Requires-Dist: urllib3>=1.26.6
Requires-Dist: tqdm>=4.41.0
Requires-Dist: PyYAML>=5.3.1
Requires-Dist: requests-toolbelt
Requires-Dist: filetype
Requires-Dist: pi-heif<2; python_version >= "3.10"
Provides-Extra: desktop
Requires-Dist: opencv-python==4.8.0.74; extra == "desktop"
Provides-Extra: dev
Requires-Dist: mypy; extra == "dev"
Requires-Dist: responses; extra == "dev"
Requires-Dist: ruff; extra == "dev"
Requires-Dist: twine; extra == "dev"
Requires-Dist: types-pyyaml; extra == "dev"
Requires-Dist: types-requests; extra == "dev"
Requires-Dist: types-setuptools; extra == "dev"
Requires-Dist: types-tqdm; extra == "dev"
Requires-Dist: wheel; extra == "dev"
